{
  "customers": [
    {
      "id": 1,
      "date": "2019-03-07",
      "custName": "shalini",
      "relation": "S/O",
      "relName": "Naresh Singh",
      "village": "begulal Khera",
      "phone": "8193920739",
      "ornaments": [
        {
          "ornament": "ring",
          "metal": "gold",
          "weight": "2",
          "rupees": "4000"
        },
        {
          "ornament": "chain",
          "metal": "gold",
          "weight": "2",
          "rupees": "5000"
        }
      ]
    },
    {
      "id": 2,
      "date": "2019-03-17",
      "custName": "samarpit verma",
      "relation": "S/O",
      "relName": "R K Verma",
      "village": "malawan",
      "phone": "8899822074",
      "ornaments": [
        {
          "ornament": "ring",
          "metal": "gold",
          "weight": "2",
          "rupees": "4000"
        }
      ]
    },
    {
      "id": 3,
      "date": 0.0003714710252600297,
      "custName": "shalini singh",
      "relation": "D/O",
      "relName": "Sunita Singh",
      "village": "begulal khaira",
      "phone": "98767887766",
      "ornaments": [
        {
          "ornament": "ring",
          "metal": "gold",
          "weight": "2",
          "rupees": "4000"
        },
        {
          "ornament": "chain",
          "metal": "gold",
          "weight": "2",
          "rupees": "5000"
        }
      ]
    },
    {
      "id": 4,
      "date": "2019-03-05",
      "custName": "arpit kumar",
      "relation": "S/O",
      "relName": "R K Verma",
      "village": "malawan",
      "phone": "8285555156",
      "ornaments": [
        {
          "ornament": "chain",
          "metal": "Gold",
          "weight": "10",
          "rupees": "15000"
        },
        {
          "ornament": "ring",
          "metal": "Gold",
          "weight": "2.5",
          "rupees": "5000"
        }
      ]
    },
    {
      "id": 5,
      "date": 0.0003714710252600297,
      "custName": "Phool Devi",
      "relation": "D/O",
      "relName": "Ram  Ladete",
      "village": "Akbarpur",
      "phone": "9877664331",
      "ornaments": [
        {
          "ornament": "Paajeb",
          "metal": "Silver",
          "weight": 100,
          "rupees": 2500
        },
        {
          "ornament": "Chain",
          "metal": "Gold",
          "weight": 10,
          "rupees": 15000
        },
        {
          "ornament": "Ring",
          "metal": "Gold",
          "weight": 5,
          "rupees": 8000
        },
        {
          "ornament": "Half Kardhani",
          "metal": "Silver",
          "weight": 200,
          "rupees": 6000
        },
        {
          "ornament": "necklace",
          "metal": "Gold",
          "weight": 30,
          "rupees": 45000
        }
      ]
    }
  ]
}